.travis.yml
README.rst
base.cfg
bootstrap.py
buildout.cfg
development.cfg
pre-commit-check.sh
rtd_requirements.txt
setup.cfg
setup.py
travis.cfg
versions.cfg
docs/HISTORY.rst
docs/LICENSE.rst
docs/conf.py
docs/conventions.rst
docs/dev.rst
docs/index.rst
docs/release.rst
docs/source.rst
src/niteoweb/__init__.py
src/niteoweb.jvzoo.egg-info/PKG-INFO
src/niteoweb.jvzoo.egg-info/SOURCES.txt
src/niteoweb.jvzoo.egg-info/dependency_links.txt
src/niteoweb.jvzoo.egg-info/entry_points.txt
src/niteoweb.jvzoo.egg-info/namespace_packages.txt
src/niteoweb.jvzoo.egg-info/not-zip-safe
src/niteoweb.jvzoo.egg-info/requires.txt
src/niteoweb.jvzoo.egg-info/top_level.txt
src/niteoweb/jvzoo/__init__.py
src/niteoweb/jvzoo/config.py
src/niteoweb/jvzoo/configure.zcml
src/niteoweb/jvzoo/interfaces.py
src/niteoweb/jvzoo/browser/__init__.py
src/niteoweb/jvzoo/browser/cancel_email.pt
src/niteoweb/jvzoo/browser/configure.zcml
src/niteoweb/jvzoo/browser/controlpanel.py
src/niteoweb/jvzoo/browser/email.pt
src/niteoweb/jvzoo/browser/jvzoo.py
src/niteoweb/jvzoo/browser/jvzoo_icon.png
src/niteoweb/jvzoo/profiles/default/controlpanel.xml
src/niteoweb/jvzoo/profiles/default/memberdata_properties.xml
src/niteoweb/jvzoo/profiles/default/metadata.xml
src/niteoweb/jvzoo/profiles/default/propertiestool.xml
src/niteoweb/jvzoo/profiles/default/registry.xml
src/niteoweb/jvzoo/profiles/default/rolemap.xml
src/niteoweb/jvzoo/tests/__init__.py
src/niteoweb/jvzoo/tests/base.py
src/niteoweb/jvzoo/tests/control_panel.txt
src/niteoweb/jvzoo/tests/test_doctest.py
src/niteoweb/jvzoo/tests/test_jvzoo.py
src/niteoweb/jvzoo/tests/test_setup.py