Metadata-Version: 1.0
Name: niteoweb.jvzoo
Version: 0.3
Summary: Integrates JVZoo digital products retailer system with Plone for paid memberships.
Home-page: http://www.niteoweb.com
Author: NiteoWeb Ltd.
Author-email: info@niteoweb.com
License: BSD
Keywords: Plone Python JVZoo
Platform: UNKNOWN
Classifier: Framework :: Plone
Classifier: Programming Language :: Python
